resources/__init__.py
resources/svl.lark
svl/__init__.py
svl/_version.py
svl/cli.py
svl/errors.py
svl/layout.py
svl/plot_validators.py
svl/sqlite.py
svl/svl.py
svl/plotly/__init__.py
svl/plotly/plotly.py
svl/plotly/templates/__init__.py
svl/plotly/templates/index.jinja
svl-0.1a4.dist-info/METADATA
svl-0.1a4.dist-info/RECORD
svl-0.1a4.dist-info/WHEEL
svl-0.1a4.dist-info/entry_points.txt
svl-0.1a4.dist-info/top_level.txt
