Metadata-Version: 2.1
Name: svl
Version: 0.1a4
Summary: UNKNOWN
Home-page: https://github.com/timothyrenner/svl
Author: Tim Renner
License: MIT
Platform: UNKNOWN
Classifier: Development Status :: 3 - Alpha
Classifier: License :: OSI Approved :: MIT License
Classifier: Programming Language :: Python :: 3.5
Classifier: Programming Language :: Python :: 3.6
Classifier: Programming Language :: Python :: 3.7
Provides-Extra: parquet
Requires-Dist: click (==6.7)
Requires-Dist: toolz (==0.9.0)
Requires-Dist: lark-parser (==0.6.6)
Requires-Dist: Jinja2 (==2.10)
Requires-Dist: pandas (==0.23.4)
Provides-Extra: parquet
Requires-Dist: pyarrow (==0.12.0); extra == 'parquet'
